pycork/__init__.py
pycork/pycork.cp39-win_amd64.pyd
pycork-0.1.3.dist-info/LICENSE
pycork-0.1.3.dist-info/METADATA
pycork-0.1.3.dist-info/WHEEL
pycork-0.1.3.dist-info/top_level.txt
pycork-0.1.3.dist-info/RECORD
