Metadata-Version: 2.1
Name: pycork
Version: 0.1.3
Summary: pycork provides a fully compiled interface to the cork boolean library 
Home-page: https://github.com/drlukeparry/pycork
Author: Luke Parry
Author-email: dev@lukeparry.uk
License: UNKNOWN
Project-URL: Documentation, https://github.com/drylukeparry/pycork
Project-URL: Source, https://github.com/drylukeparry/pycork
Project-URL: Tracker, https://github.com/drlukeparry/pycork/issues
Keywords: Boolean CSG,Cork
Platform: UNKNOWN
Classifier: Programming Language :: Python
Classifier: Programming Language :: Python :: 3.5
Classifier: Programming Language :: Python :: 3.6
Classifier: Programming Language :: Python :: 3.7
Classifier: Programming Language :: Python :: 3.8
Classifier: Programming Language :: Python :: 3.9
Classifier: Programming Language :: Python :: 3.10
Classifier: Natural Language :: English
Classifier: Topic :: Scientific/Engineering
License-File: LICENSE
